{
  "id": "local:ea:concept:cybernetic-feedback",
  "kind": "local",
  "focus": "ea:concept:cybernetic-feedback",
  "nodes": [
    {
      "id": "ea:concept:cybernetic-feedback",
      "type": "concept",
      "title": "Cybernetic Feedback",
      "route": "/knowledge/concepts/cybernetic-feedback/",
      "status": "active",
      "confidence": "validated"
    },
    {
      "id": "ea:publication:generative-systems-cybernetics-and-creative-coding",
      "type": "publication",
      "title": "Generative Systems, Cybernetics and Creative Coding",
      "route": "/publications/generative-systems-cybernetics-and-creative-coding/",
      "status": "active",
      "confidence": "published"
    },
    {
      "id": "ea:publication:algorithmic-composition-and-rule-based-music",
      "type": "publication",
      "title": "Algorithmic Composition and Rule-Based Music",
      "route": "/publications/algorithmic-composition-and-rule-based-music/",
      "status": "active",
      "confidence": "published"
    },
    {
      "id": "ea:publication:systems-thinking-for-creative-practice",
      "type": "publication",
      "title": "Systems Thinking for Creative Practice",
      "route": "/publications/systems-thinking-for-creative-practice/",
      "status": "active",
      "confidence": "published"
    },
    {
      "id": "ea:collection:knowledge-hub-foundations",
      "type": "collection",
      "title": "Knowledge Hub Foundations",
      "route": "/archive/collections/knowledge-hub-foundations/",
      "status": "active",
      "confidence": "published"
    }
  ],
  "edges": [
    {
      "id": "ear:generative-systems-article-documents-cybernetic-feedback",
      "source": "ea:publication:generative-systems-cybernetics-and-creative-coding",
      "target": "ea:concept:cybernetic-feedback",
      "predicate": "documents",
      "label": "Documents",
      "statement": "Generative Systems, Cybernetics and Creative Coding uses cybernetic feedback as a historical and technical foundation.",
      "confidence": "published"
    },
    {
      "id": "ear:algorithmic-composition-article-documents-cybernetic-feedback",
      "source": "ea:publication:algorithmic-composition-and-rule-based-music",
      "target": "ea:concept:cybernetic-feedback",
      "predicate": "documents",
      "label": "Documents",
      "statement": "Algorithmic Composition and Rule-Based Music connects feedback loops to musical systems.",
      "confidence": "published"
    },
    {
      "id": "ear:systems-thinking-article-documents-cybernetic-feedback",
      "source": "ea:publication:systems-thinking-for-creative-practice",
      "target": "ea:concept:cybernetic-feedback",
      "predicate": "documents",
      "label": "Documents",
      "statement": "Systems Thinking for Creative Practice connects system behavior to cybernetic feedback.",
      "confidence": "published"
    },
    {
      "id": "ear:cybernetic-feedback-member-of-collection-knowledge-hub-foundations",
      "source": "ea:concept:cybernetic-feedback",
      "target": "ea:collection:knowledge-hub-foundations",
      "predicate": "memberOfCollection",
      "label": "Member of collection",
      "statement": "Cybernetic Feedback is an explicit member of the Knowledge Hub Foundations collection.",
      "confidence": "validated"
    }
  ]
}
